full_adder.v
module full_adder(a, b, cin, s, cout);
 input a, b, cin;
 output s, cout;
 assign s = a ^ b ^ cin;
 assign cout = (a&b) | (b&cin) | (cin&a);
endmodule

binary_adder.v
module binary_adder(a, b, cin, sum, cout);
 input [2:0]a,b;
 input cin;
 output [2:0]cout;
 output[2:0]sum;
 full_adder F1(.a(a[0]), .b(b[0]), .cin(cin), .s(sum[0]), .cout(cout[0]));
 full_adder F2(.a(a[1]), .b(b[1]), .cin(cout[0]), .s(sum[1]), .cout(cout[1]));
 full_adder F3(.a(a[2]), .b(b[2]), .cin(cout[1]), .s(sum[2]), .cout(cout[2]));
endmodule

binary_adder_tb.v
module binary_adder_tb;
reg [2:0]a, b;
reg cin;
wire [2:0]sum, cout;
binary_adder DUT(a, b, cin, sum, cout);
initial
begin
    $dumpfile("binary_adder_tb.vcd");
    $dumpvars(0, binary_adder_tb);
end
initial
begin
    $display("binary adder simulation using 3 full adders");
    $monitor("a = %b, b = %b, cin = %b, sum = %b, cout = %b", a, b, cin, sum, cout);
    a = 3'b000; b = 3'b000; cin = 0; #5;
    a = 3'b000; b = 3'b000; cin = 1; #5;
    a = 3'b000; b = 3'b001; cin = 0; #5;
    a = 3'b000; b = 3'b001; cin = 1; #5;
    a = 3'b000; b = 3'b010; cin = 0; #5;
    a = 3'b000; b = 3'b010; cin = 1; #5;
    a = 3'b000; b = 3'b011; cin = 0; #5;
    a = 3'b000; b = 3'b011; cin = 1; #5;
    a = 3'b001; b = 3'b001; cin = 0; #5;
    a = 3'b001; b = 3'b001; cin = 1; #5;
    a = 3'b100; b = 3'b010; cin = 0; #5;
    a = 3'b100; b = 3'b010; cin = 1; #5;
end
endmodule

binary_adder_tb.vcd
$date
	Mon Jun 22 13:39:01 2026
$end
$version
	Icarus Verilog
$end
$timescale
	1s
$end
$scope module binary_adder_tb $end
$var wire 3 ! sum [2:0] $end
$var wire 3 " cout [2:0] $end
$var reg 3 # a [2:0] $end
$var reg 3 $ b [2:0] $end
$var reg 1 % cin $end
$scope module DUT $end
$var wire 3 & a [2:0] $end
$var wire 3 ' b [2:0] $end
$var wire 1 % cin $end
$var wire 3 ( sum [2:0] $end
$var wire 3 ) cout [2:0] $end
$scope module F1 $end
$var wire 1 * a $end
$var wire 1 + b $end
$var wire 1 % cin $end
$var wire 1 , cout $end
$var wire 1 - s $end
$upscope $end
$scope module F2 $end
$var wire 1 . a $end
$var wire 1 / b $end
$var wire 1 0 cin $end
$var wire 1 1 cout $end
$var wire 1 2 s $end
$upscope $end
$scope module F3 $end
$var wire 1 3 a $end
$var wire 1 4 b $end
$var wire 1 5 cin $end
$var wire 1 6 cout $end
$var wire 1 7 s $end
$upscope $end
$upscope $end
$upscope $end
$enddefinitions $end
$comment Show the parameter values. $end
$dumpall
$end
#0
$dumpvars
07
06
05
04
03
02
01
00
0/
0.
0-
0,
0+
0*
b0 )
b0 (
b0 '
b0 &
0%
b0 $
b0 #
b0 "
b0 !
$end
#5
b1 !
b1 (
1-
1%
#10
b1 !
b1 (
1-
1+
0%
b1 $
b1 '
#15
12
10
b1 "
b1 )
1,
b10 !
b10 (
0-
1%
#20
07
05
00
b0 "
b0 )
01
0,
12
b10 !
b10 (
0-
0+
1/
0%
b10 $
b10 '
#25
b11 !
b11 (
1-
1%
#30
b11 !
b11 (
1-
1+
0%
b11 $
b11 '
#35
17
15
11
02
10
b11 "
b11 )
1,
b100 !
b100 (
0-
1%
#40
07
05
b1 "
b1 )
01
12
b10 !
b10 (
0-
0/
1*
0%
b1 $
b1 '
b1 #
b1 &
#45
b11 !
b11 (
1-
1%
#50
06
05
00
b0 "
b0 )
01
0,
12
17
b110 !
b110 (
0-
0+
1/
0*
13
0%
b10 $
b10 '
b100 #
b100 &
#55
b111 !
b111 (
1-
1%
