circuit_1.v
module circuit_1(A, B, Z);
 input [1:0]A, B;
 output reg Z;
 always @(*)
 begin
  if (A == B)
    Z = 1;
  else
    Z = 0;
 end
endmodule

circuit_1_tb.v
module circuit_1_tb;
 reg [1:0]A, B;
 wire Z;
 circuit_1 DUT(A, B, Z);
 initial
 begin
    $dumpfile("circuit_1_tb.vcd");
    $dumpvars(0, circuit_1_tb);
 end
 initial
 begin
    $display("circuit_1 simulation:");
    $monitor("A = %b, B = %b, Z = %b", A, B, Z);
    A = 2'b00; B = 2'b00; #10;
    A = 2'b00; B = 2'b01; #10;
    A = 2'b00; B = 2'b10; #10;
    A = 2'b00; B = 2'b11; #10;
    A = 2'b01; B = 2'b00; #10;
    A = 2'b01; B = 2'b01; #10;
    A = 2'b01; B = 2'b10; #10;
    A = 2'b01; B = 2'b11; #10;
    A = 2'b10; B = 2'b00; #10;
    A = 2'b10; B = 2'b01; #10;
    A = 2'b10; B = 2'b10; #10;
    A = 2'b10; B = 2'b11; #10;
    A = 2'b11; B = 2'b11; #10;
    $finish;
 end
endmodule

circuit_1_tb.vcd
$date
	Fri Jun 19 15:42:22 2026
$end
$version
	Icarus Verilog
$end
$timescale
	1s
$end
$scope module circuit_1_tb $end
$var wire 1 ! Z $end
$var reg 2 " A [1:0] $end
$var reg 2 # B [1:0] $end
$scope module DUT $end
$var wire 2 $ A [1:0] $end
$var wire 2 % B [1:0] $end
$var reg 1 ! Z $end
$upscope $end
$upscope $end
$enddefinitions $end
$comment Show the parameter values. $end
$dumpall
$end
#0
$dumpvars
b0 %
b0 $
b0 #
b0 "
1!
$end
#10
0!
b1 #
b1 %
#20
b10 #
b10 %
#30
b11 #
b11 %
#40
b0 #
b0 %
b1 "
b1 $
#50
1!
b1 #
b1 %
#60
0!
b10 #
b10 %
#70
b11 #
b11 %
#80
b0 #
b0 %
b10 "
b10 $
#90
b1 #
b1 %
#100
1!
b10 #
b10 %
#110
0!
b11 #
b11 %
#120
1!
b11 "
b11 $
