example_2.v
module example_2(vec, outvec, o2, o1, o0);
 input [2:0]vec;
 output [2:0]outvec;
 output o2, o1, o0;
 assign outvec = vec;
 assign o2 = vec[2];
 assign o1 = vec[1];
 assign o0 = vec[0];
endmodule

example_2_tb.v
module example_2_tb;
 reg [2:0]vec;
 wire [2:0]outvec;
 wire o2, o1, o0;
 example_2 DUT(vec, outvec, o2, o1, o0);
 initial 
 begin
    $dumpfile("example_2_tb.vcd");
    $dumpvars(0, example_2_tb);
 end
 initial
 begin
    $display("example_2 simulation:");
    $monitor("vec = %b, outvec = %b, o2 = %b, o1 = %b, o0 = %b", vec, outvec, o2, o1, o0);
    vec = 3'b000; #10;
    vec = 3'b001; #10;
    vec = 3'b010; #10;
    vec = 3'b011; #10;
    vec = 3'b100; #10;
    vec = 3'b101; #10;
    vec = 3'b110; #10;
    vec = 3'b111; #10;
    $finish;
 end
endmodule

example_2_tb.vcd
$date
	Thu Jun 18 20:04:31 2026
$end
$version
	Icarus Verilog
$end
$timescale
	1s
$end
$scope module example_2_tb $end
$var wire 3 ! outvec [2:0] $end
$var wire 1 " o2 $end
$var wire 1 # o1 $end
$var wire 1 $ o0 $end
$var reg 3 % vec [2:0] $end
$scope module DUT $end
$var wire 3 & outvec [2:0] $end
$var wire 3 ' vec [2:0] $end
$var wire 1 " o2 $end
$var wire 1 # o1 $end
$var wire 1 $ o0 $end
$upscope $end
$upscope $end
$enddefinitions $end
$comment Show the parameter values. $end
$dumpall
$end
#0
$dumpvars
b0 '
b0 &
b0 %
0$
0#
0"
b0 !
$end
#10
1$
b1 !
b1 &
b1 %
b1 '
#20
1#
0$
b10 !
b10 &
b10 %
b10 '
#30
1$
b11 !
b11 &
b11 %
b11 '
#40
1"
0#
0$
b100 !
b100 &
b100 %
b100 '
#50
1$
b101 !
b101 &
b101 %
b101 '
#60
1#
0$
b110 !
b110 &
b110 %
b110 '
#70
1$
b111 !
b111 &
b111 %
b111 '
