four_bit_synchronous_counter.v
module four_bit_synchronous_counter(clk, clear, count_enable, Q, Qbar);
 input clk, clear, count_enable;
 output reg [3:0]Q;
 output [3:0]Qbar;
 assign Qbar = ~Q;
 always @(negedge clk or negedge clear)
 begin
    if(!clear)
        Q <= 4'b000;
    else if(count_enable)
        Q <= Q + 1;
    else
        Q <= Q;
 end
endmodule

four_bit_synchronous_counter_tb.v
module four_bit_synchronous_counter_tb;
 reg clk, clear, count_enable;
 wire [3:0]Q, Qbar;
 four_bit_synchronous_counter BUT(clk, clear, count_enable, Q, Qbar);
 initial
 begin
    clk = 0;
    forever #5 clk = ~clk;
 end
 initial
 begin
    $dumpfile("four_bit_synchronous_counter_tb.vcd");
    $dumpvars(0, four_bit_synchronous_counter_tb);
 end
 initial
 begin
    $display("four bit counter simulation");
    $monitor("time = %0t, clk = %b, clear = %b, count_enable = %b, Q = %b, Qbar = %b",$time, clk, clear, count_enable, Q, Qbar);
    clear = 0;
    count_enable = 0;
    #12;
    clear = 1;
    count_enable = 1;
    #80;
    count_enable = 0;
    #30;
    count_enable = 1;
  #140;
    $finish;
 end
endmodule

four_bit_synchronous_counter_tb.vcd
$date
	Thu Jun 25 14:09:17 2026
$end
$version
	Icarus Verilog
$end
$timescale
	1s
$end
$scope module four_bit_synchronous_counter_tb $end
$var wire 4 ! Qbar [3:0] $end
$var wire 4 " Q [3:0] $end
$var reg 1 # clear $end
$var reg 1 $ clk $end
$var reg 1 % count_enable $end
$scope module BUT $end
$var wire 4 & Qbar [3:0] $end
$var wire 1 # clear $end
$var wire 1 $ clk $end
$var wire 1 % count_enable $end
$var reg 4 ' Q [3:0] $end
$upscope $end
$upscope $end
$enddefinitions $end
$comment Show the parameter values. $end
$dumpall
$end
#0
$dumpvars
b0 '
b1111 &
0%
0$
0#
b0 "
b1111 !
$end
#5
1$
#10
0$
#12
1%
1#
#15
1$
#20
b1110 !
b1110 &
b1 "
b1 '
0$
#25
1$
#30
b1101 !
b1101 &
b10 "
b10 '
0$
#35
1$
#40
b1100 !
b1100 &
b11 "
b11 '
0$
#45
1$
#50
b1011 !
b1011 &
b100 "
b100 '
0$
#55
1$
#60
b1010 !
b1010 &
b101 "
b101 '
0$
#65
1$
#70
b1001 !
b1001 &
b110 "
b110 '
0$
#75
1$
#80
b1000 !
b1000 &
b111 "
b111 '
0$
#85
1$
#90
b111 !
b111 &
b1000 "
b1000 '
0$
#92
0%
#95
1$
#100
0$
#105
1$
#110
0$
#115
1$
#120
0$
#122
1%
#125
1$
#130
b110 !
b110 &
b1001 "
b1001 '
0$
#135
1$
#140
b101 !
b101 &
b1010 "
b1010 '
0$
#145
1$
#150
b100 !
b100 &
b1011 "
b1011 '
0$
#155
1$
#160
b11 !
b11 &
b1100 "
b1100 '
0$
#165
1$
#170
b10 !
b10 &
b1101 "
b1101 '
0$
#175
1$
#180
b1 !
b1 &
b1110 "
b1110 '
0$
#185
1$
#190
b0 !
b0 &
b1111 "
b1111 '
0$
#195
1$
#200
b1111 !
b1111 &
b0 "
b0 '
0$
#205
1$
#210
b1110 !
b1110 &
b1 "
b1 '
0$
#215
1$
#220
b1101 !
b1101 &
b10 "
b10 '
0$
#225
1$
#230
b1100 !
b1100 &
b11 "
b11 '
0$
#235
1$
#240
b1011 !
b1011 &
b100 "
b100 '
0$
#245
1$
#250
b1010 !
b1010 &
b101 "
b101 '
0$
#255
1$
#260
b1001 !
b1001 &
b110 "
b110 '
0$
