full_subtractor.v
module full_subtractor(x, y, z, d, b);
 input x, y, z;
 output d, b;
 assign d = x ^ y ^ z;
 assign b = ~x & (y ^ z) | y & z;
endmodule

full_subtractor_tb.v
module full_subtractor_tb;
 reg x, y, z;
 wire d, b;
 full_subtractor DUT(x, y, z, d, b);
 initial
 begin
    $dumpfile("full_subtractor_tb.vcd");
    $dumpvars(0, full_subtractor_tb);
 end
 initial
 begin
    $display("full_subtractor simulation");
    $monitor("x = %b, y = %b, z = %b, d = %b, b = %b", x, y, z, d, b);
    x = 0; y = 0; z = 0; #4;
    x = 0; y = 0; z = 1; #4;
    x = 0; y = 1; z = 0; #4;
    x = 0; y = 1; z = 1; #4;
    x = 1; y = 0; z = 0; #4;
    x = 1; y = 0; z = 1; #4;
    x = 1; y = 1; z = 0; #4;
    x = 1; y = 1; z = 1; #4;
 end
endmodule

full_subtractor_tb.vcd
$date
	Thu Jun 25 11:14:51 2026
$end
$version
	Icarus Verilog
$end
$timescale
	1s
$end
$scope module full_subtractor_tb $end
$var wire 1 ! d $end
$var wire 1 " b $end
$var reg 1 # x $end
$var reg 1 $ y $end
$var reg 1 % z $end
$scope module DUT $end
$var wire 1 " b $end
$var wire 1 ! d $end
$var wire 1 # x $end
$var wire 1 $ y $end
$var wire 1 % z $end
$upscope $end
$upscope $end
$enddefinitions $end
$comment Show the parameter values. $end
$dumpall
$end
#0
$dumpvars
0%
0$
0#
0"
0!
$end
#4
1"
1!
1%
#8
0%
1$
#12
0!
1%
#16
0"
1!
0%
0$
1#
#20
0!
1%
#24
0%
1$
#28
1"
1!
1%
