jk_ff.v
module jk_ff(clk, J, K, Q, Qbar);
 input clk, J, K;
 output reg Q;
 output Qbar;
 assign Qbar = ~Q;
 always @(posedge clk)
 begin
    if(J == 0 && K == 0)
        Q <= Q;
    else if(J == 0 && K == 1)
        Q <= 0;
    else if(J == 1 && K == 0)
        Q <= 1;
    else if(J == 1 && K == 1)
        Q <= ~Q;
 end
endmodule

jk_ff_tb.v
module jk_ff_tb;
 reg clk, J, K;
 wire Q, Qbar;
 jk_ff DUT(clk, J, K, Q, Qbar);
 initial
 begin
    clk = 0;
    forever #5 clk = ~clk;
 end
 initial
 begin
    $dumpfile("jk_ff_tb.vcd");
    $dumpvars(0, jk_ff_tb);
 end
 initial
 begin
    $display("jk_ff simulation:");
    $monitor("$time = %0t, clk = %b, J = %b, K = %b, Q = %b, Qbar = %b", $time, clk, J, K, Q, Qbar);
    J=0; K=0; #10;
    J=0; K=1; #10;
    J=1; K=0; #10;
    J=1; K=1; #10;
    J=1; K=1; #10;
    J=0; K=0; #10;
    $finish;
 end
endmodule

jk_ff_tb.vcd
$date
	Fri Jun 26 12:34:35 2026
$end
$version
	Icarus Verilog
$end
$timescale
	1s
$end
$scope module jk_ff_tb $end
$var wire 1 ! Qbar $end
$var wire 1 " Q $end
$var reg 1 # J $end
$var reg 1 $ K $end
$var reg 1 % clk $end
$scope module DUT $end
$var wire 1 # J $end
$var wire 1 $ K $end
$var wire 1 ! Qbar $end
$var wire 1 % clk $end
$var reg 1 " Q $end
$upscope $end
$upscope $end
$enddefinitions $end
$comment Show the parameter values. $end
$dumpall
$end
#0
$dumpvars
0%
0$
0#
x"
x!
$end
#5
1%
#10
0%
1$
#15
1!
0"
1%
#20
0%
0$
1#
#25
0!
1"
1%
#30
0%
1$
#35
1!
0"
1%
#40
0%
#45
0!
1"
1%
#50
0%
0$
0#
