led_blinker.v
module led_blinker(clk, reset, out);
 input clk, reset;
 output reg out;
 reg [2:0]count;
 always@(posedge clk)
 begin
    if(reset) begin
        count <= 3'b000;
        out <= 1'b0;
    end
    else if (count == 3'd4) begin
        count <= 3'b000;
        out <= ~out;
    end
    else begin
        count <= count + 1;
    end
 end
endmodule

led_blinker_tb.v
module led_blinker_tb;
 reg clk, reset;
 wire out;
 led_blinker DUT(clk, reset, out);
 initial
 begin
    clk = 0;
    forever #5 clk = ~clk;
 end
 initial
 begin
    $dumpfile("led_blinker_tb.vcd");
    $dumpvars(0, led_blinker_tb);
 end
 initial
 begin
    $display("led blinker project");
    $monitor("time = %0t, clk = %b, reset = %b, out = %b", $time, clk, reset, out);
    reset = 1'b0; #5;
    reset = 1'b1; #10;
    reset = 1'b0; #10;
    reset = 1'b0; #10;
    reset = 1'b0; #10;
    reset = 1'b0; #10;
    reset = 1'b0; #10;
    reset = 1'b0; #10;
    $finish;
 end
endmodule

led_blinker_tb.vcd
$date
	Tue Jul 28 21:15:26 2026
$end
$version
	Icarus Verilog
$end
$timescale
	1s
$end
$scope module led_blinker_tb $end
$var wire 1 ! out $end
$var reg 1 " clk $end
$var reg 1 # reset $end
$scope module DUT $end
$var wire 1 $ clk $end
$var wire 1 % reset $end
$var reg 3 & count [2:0] $end
$var reg 1 ' out $end
$upscope $end
$upscope $end
$enddefinitions $end
#0
$dumpvars
x'
bx &
0%
0$
0#
0"
x!
$end
#5
0'
0!
b0 &
1#
1%
1"
1$
#10
0"
0$
#15
b1 &
1"
1$
0#
0%
#20
0"
0$
#25
b10 &
1"
1$
#30
0"
0$
#35
b11 &
1"
1$
#40
0"
0$
#45
b100 &
1"
1$
#50
0"
0$
#55
1'
1!
b0 &
1"
1$
#60
0"
0$
#65
b1 &
1"
1$
#70
0"
0$
#75
b10 &
1"
1$
