mux_2_1.v
module mux_2_1(a, b, s0, y);
 input a, b, s0;
 output y;
 assign y = s0?b:a;
endmodule

mux_4_1.v
module mux_4_1(a, b, c, d, s0, s1, y);
 input a, b, c, d, s0, s1;
 output y;
 wire y1, y2;
 mux_2_1 M1(.a(a), .b(b), .s0(s0), .y(y1));
 mux_2_1 M2(.a(c), .b(d), .s0(s0), .y(y2));
 mux_2_1 M3(.a(y1), .b(y2), .s0(s1), .y(y));
endmodule

mux_4_1_tb.v
module mux_4_1_tb;
 reg a, b, c, d, s0, s1;
 wire y;
 wire y1, y2;
 mux_4_1 DUT(a, b, c, d, s0, s1, y);
 initial
 begin
    $dumpfile("mux_4_1_tb.vcd");
    $dumpvars(0, mux_4_1_tb);
 end
 initial
 begin
    $display("mux_4_1 using mux_2_1");
    $monitor("a = %b, b = %b, c = %b, d = %b, s0 = %b, s1 = %b, y = %b", a, b, c, d, s0, s1, y);
    a = 0; b = 0; c = 0; d = 0; s0 = 0; s1 = 0; #10;
    a = 0; b = 0; c = 0; d = 0; s0 = 0; s1 = 1; #10;
    a = 0; b = 0; c = 0; d = 0; s0 = 1; s1 = 0; #10;
    a = 0; b = 0; c = 0; d = 0; s0 = 1; s1 = 1; #10;
    a = 0; b = 0; c = 0; d = 1; s0 = 0; s1 = 0; #10;
    a = 0; b = 0; c = 0; d = 1; s0 = 0; s1 = 1; #10;
    a = 0; b = 0; c = 0; d = 1; s0 = 1; s1 = 0; #10;
    a = 0; b = 0; c = 0; d = 1; s0 = 1; s1 = 1; #10;
    a = 0; b = 0; c = 1; d = 0; s0 = 0; s1 = 0; #10;
    a = 0; b = 0; c = 1; d = 0; s0 = 0; s1 = 1; #10;
    a = 0; b = 0; c = 1; d = 0; s0 = 1; s1 = 0; #10;
    a = 0; b = 0; c = 1; d = 0; s0 = 1; s1 = 1; #10;
    a = 0; b = 0; c = 1; d = 1; s0 = 0; s1 = 0; #10;
    a = 0; b = 0; c = 1; d = 1; s0 = 0; s1 = 1; #10;
    a = 0; b = 0; c = 1; d = 1; s0 = 1; s1 = 0; #10;
    a = 0; b = 0; c = 1; d = 1; s0 = 1; s1 = 1; #10;
 end
endmodule

mux_4_1_tb.vcd
$date
	Mon Jun 22 12:21:01 2026
$end
$version
	Icarus Verilog
$end
$timescale
	1s
$end
$scope module mux_4_1_tb $end
$var wire 1 ! y $end
$var reg 1 " a $end
$var reg 1 # b $end
$var reg 1 $ c $end
$var reg 1 % d $end
$var reg 1 & s0 $end
$var reg 1 ' s1 $end
$scope module DUT $end
$var wire 1 " a $end
$var wire 1 # b $end
$var wire 1 $ c $end
$var wire 1 % d $end
$var wire 1 & s0 $end
$var wire 1 ' s1 $end
$var wire 1 ( y2 $end
$var wire 1 ) y1 $end
$var wire 1 ! y $end
$scope module M1 $end
$var wire 1 " a $end
$var wire 1 # b $end
$var wire 1 & s0 $end
$var wire 1 ) y $end
$upscope $end
$scope module M2 $end
$var wire 1 $ a $end
$var wire 1 % b $end
$var wire 1 & s0 $end
$var wire 1 ( y $end
$upscope $end
$scope module M3 $end
$var wire 1 ) a $end
$var wire 1 ( b $end
$var wire 1 ' s0 $end
$var wire 1 ! y $end
$upscope $end
$upscope $end
$upscope $end
$enddefinitions $end
$comment Show the parameter values. $end
$dumpall
$end
#0
$dumpvars
0)
0(
0'
0&
0%
0$
0#
0"
0!
$end
#10
1'
#20
0'
1&
#30
1'
#40
0'
0&
1%
#50
1'
#60
1(
0'
1&
#70
1!
1'
#80
0!
0'
0&
0%
1$
#90
1!
1'
#100
0!
0(
0'
1&
#110
1'
#120
1(
0'
0&
1%
#130
1!
1'
#140
0!
0'
1&
#150
1!
1'
