mux_2_1.v
module mux_2_1(a, b, s0, y);
 input a, b, s0;
 output y;
 assign y = s0?b:a;
endmodule

mux_2_1_tb.v
module mux_2_1_tb;
 reg a, b, s0;
 wire y;
 mux_2_1 DUT(a, b, s0, y);
 initial
 begin
    $dumpfile("mux_2_1_tb.vcd");
    $dumpvars(0, mux_2_1_tb);
 end
 initial
 begin
    $display("mux_2_1");
    $monitor("a = %b, b = %b, s0 = %b, y = %b", a, b, s0, y);
    a = 0; b = 0; s0 = 0; #5;
    a = 0; b = 0; s0 = 1; #5;
    a = 0; b = 1; s0 = 0; #5;
    a = 0; b = 1; s0 = 1; #5;
    a = 1; b = 0; s0 = 0; #5;
    a = 1; b = 0; s0 = 1; #5;
    a = 1; b = 1; s0 = 0; #5;
    a = 1; b = 1; s0 = 1; #5;
 end
endmodule

mux_2_1_tb.vcd
$date
	Thu Jun 18 17:20:59 2026
$end
$version
	Icarus Verilog
$end
$timescale
	1s
$end
$scope module mux_2_1_tb $end
$var wire 1 ! y $end
$var reg 1 " a $end
$var reg 1 # b $end
$var reg 1 $ s0 $end
$scope module DUT $end
$var wire 1 " a $end
$var wire 1 # b $end
$var wire 1 $ s0 $end
$var wire 1 ! y $end
$upscope $end
$upscope $end
$enddefinitions $end
$comment Show the parameter values. $end
$dumpall
$end
#0
$dumpvars
0$
0#
0"
0!
$end
#5
1$
#10
0$
1#
#15
1!
1$
#20
0$
0#
1"
#25
0!
1$
#30
1!
0$
1#
#35
1$
