ring_counter.v
module ring_counter(clk, reset, out);
 input clk, reset;
 output reg [3:0]out;
 always@(posedge clk)
 begin
    if(reset)
        out <= 4'b0001;
    else
        out <= {out[0], out[3:1]};
 end
endmodule

ring_counter_tb.v
module ring_counter_tb;
 reg clk, reset;
 wire [3:0]out;
 ring_counter DUT(clk, reset, out);
 initial
 begin
    clk = 0;
    forever #5 clk = ~clk;
 end
 initial
 begin
    $dumpfile("ring_counter_tb.vcd");
    $dumpvars(0, ring_counter_tb);
 end
 initial
 begin
    $display("ring counter simulation");
    $monitor("clk = %b, reset = %b, out = %b", clk, reset, out);
    reset = 1'b0; #5;
    reset = 1'b0; #10;
    reset = 1'b1; #10;
    reset = 1'b0; #10;
    reset = 1'b0; #10;
    reset = 1'b0; #10;
    reset = 1'b0; #10;
    reset = 1'b0; #10;
    reset = 1'b0; #10;
    $finish;
 end
endmodule

ring_counter_tb.vcd
$date
	Tue Jul 28 11:35:06 2026
$end
$version
	Icarus Verilog
$end
$timescale
	1s
$end
$scope module ring_counter_tb $end
$var wire 4 ! out [3:0] $end
$var reg 1 " clk $end
$var reg 1 # reset $end
$scope module DUT $end
$var wire 1 $ clk $end
$var wire 1 % reset $end
$var reg 4 & out [3:0] $end
$upscope $end
$upscope $end
$enddefinitions $end
#0
$dumpvars
bx &
0%
0$
0#
0"
bx !
$end
#5
1"
1$
#10
0"
0$
#15
b1 &
b1 !
1"
1$
1#
1%
#20
0"
0$
#25
b1000 &
b1000 !
1"
1$
0#
0%
#30
0"
0$
#35
b100 &
b100 !
1"
1$
#40
0"
0$
#45
b10 &
b10 !
1"
1$
#50
0"
0$
#55
b1 &
b1 !
1"
1$
#60
0"
0$
#65
b1000 &
b1000 !
1"
1$
#70
0"
0$
#75
b100 &
b100 !
1"
1$
#80
0"
0$
#85
b10 &
b10 !
1"
1$
