select_led_blink.v
module select_led_blink(clk, reset, sel, out);
 input clk, reset;
 input [1:0]sel;
 output reg out;
 reg [3:0]count;
 always@(posedge clk)
 begin
   if(reset)
       count <= 4'b0000;
   else
       count <= count + 1;
 end
 always@(*)
 begin
    case(sel)
           2'b00 : out = count[3];
           2'b01 : out = count[2];
           2'b10 : out = count[1];
           2'b11 : out = count[0];
           default : out = 1'b0;
    endcase
 end
endmodule

select_led_blink_tb.v
module select_led_blink_tb;
 reg clk, reset;
 reg [1:0] sel;
 wire out;
 select_led_blink DUT(clk, reset, sel, out);
 initial
 begin
    clk = 0;
    forever #5 clk = ~clk;
 end
 initial
 begin
    $dumpfile("select_led_blink_tb.vcd");
    $dumpvars(0, select_led_blink_tb);
 end
 initial
 begin
    $display("simulation of selectable LED Blink");
    $monitor("time = %0t, clk = %b, reset = %b, sel = %b, out = %b", $time, clk, reset, sel, out);
    reset = 1'b0; sel = 2'b00; #5;
    reset = 1'b1; sel = 2'b00; #10;
    reset = 1'b0; sel = 2'b01; #10;
    reset = 1'b0; sel = 2'b01; #10;
    reset = 1'b0; sel = 2'b10; #10;
    reset = 1'b0; sel = 2'b10; #10;
    reset = 1'b0; sel = 2'b11; #10;
    reset = 1'b0; sel = 2'b11; #10;
    $finish;
 end
endmodule

select_led_blink_tb.vcd
$date
	Tue Jul 28 22:13:13 2026
$end
$version
	Icarus Verilog
$end
$timescale
	1s
$end
$scope module select_led_blink_tb $end
$var wire 1 ! out $end
$var reg 1 " clk $end
$var reg 1 # reset $end
$var reg 2 $ sel [1:0] $end
$scope module DUT $end
$var wire 1 % clk $end
$var wire 1 & reset $end
$var wire 2 ' sel [1:0] $end
$var reg 4 ( count [3:0] $end
$var reg 1 ) out $end
$upscope $end
$upscope $end
$enddefinitions $end
#0
$dumpvars
x)
bx (
b0 '
0&
0%
b0 $
0#
0"
x!
$end
#5
0)
0!
b0 (
1#
1&
1"
1%
#10
0"
0%
#15
b1 (
1"
1%
b1 $
b1 '
0#
0&
#20
0"
0%
#25
b10 (
1"
1%
#30
0"
0%
#35
b11 (
1)
1!
1"
1%
b10 $
b10 '
#40
0"
0%
#45
0)
0!
b100 (
1"
1%
#50
0"
0%
#55
1)
1!
b101 (
1"
1%
b11 $
b11 '
#60
0"
0%
#65
0)
0!
b110 (
1"
1%
#70
0"
0%
#75
1)
1!
b111 (
1"
1%
