serial_in_parallel_out.v
module serial_in_parallel_out(in, clk, reset, out);
 input in, clk, reset;
 output reg[3:0]out;
 always@(posedge clk)
 begin
    if(reset)
        out <= 4'b0000;
    else
        out <= {in, out[3:1]};
 end
endmodule

serial_in_parallel_out_tb.v
module serial_in_parallel_out_tb;
 reg in, clk, reset;
 wire [3:0]out;
 serial_in_parallel_out DUT(in, clk, reset, out);
 initial
    clk = 0;
 always #5 clk = ~clk;
 initial
 begin
    $dumpfile("serial_in_parallel_out_tb.vcd");
    $dumpvars(0, serial_in_parallel_out_tb);
 end
 initial
 begin
    $display("serial in parallel out register");
    $monitor("in = %b, clk = %b, reset = %b, out = %b", in, clk, reset, out);
    in = 1'b1; reset = 1'b0; #5;
    in = 1'b1; reset = 1'b0; #5;
    in = 1'b1; reset = 1'b0; #5;
    in = 1'b0; reset = 1'b1; #5;
    in = 1'b0; reset = 1'b1; #5;
    in = 1'b1; reset = 1'b0; #5;
    in = 1'b1; reset = 1'b0; #10;
    in = 1'b0; reset = 1'b0; #10;
    in = 1'b1; reset = 1'b0; #10;
    $finish;
 end
endmodule

serial_in_parallel_out_tb.vcd
$date
	Mon Jul 27 23:21:43 2026
$end
$version
	Icarus Verilog
$end
$timescale
	1s
$end
$scope module serial_in_parallel_out_tb $end
$var wire 4 ! out [3:0] $end
$var reg 1 " clk $end
$var reg 1 # in $end
$var reg 1 $ reset $end
$scope module DUT $end
$var wire 1 % clk $end
$var wire 1 & in $end
$var wire 1 ' reset $end
$var reg 4 ( out [3:0] $end
$upscope $end
$upscope $end
$enddefinitions $end
#0
$dumpvars
bx (
0'
1&
0%
0$
1#
0"
bx !
$end
#5
b1xxx (
b1xxx !
1"
1%
#10
0"
0%
#15
b0 (
b0 !
1$
1'
0#
0&
1"
1%
#20
0"
0%
#25
b1000 (
b1000 !
0$
0'
1#
1&
1"
1%
#30
0"
0%
#35
b1100 (
b1100 !
1"
1%
#40
0"
0%
0#
0&
#45
b110 (
b110 !
1"
1%
#50
0"
0%
1#
1&
#55
b1011 (
b1011 !
1"
1%
