universal_shift_register.v
module universal_shift_register(in, clk, reset, sel, out);
 input [3:0]in;
 input [1:0]sel;
 input clk, reset;
 output reg [3:0]out;
 always@(posedge clk)
 begin
    if(reset)
        out = 4'b0000;
    else
        case(sel)
            2'b00 : out <= out;
            2'b01 : out <= out >> 1;
            2'b10 : out <= out << 1;
            2'b11 : out <= in;
            default: out <= out;
        endcase
 end
endmodule

universal_shift_register_tb.v
module universal_shift_register_tb;
 reg [3:0]in;
 reg [1:0]sel;
 reg clk, reset;
 wire [3:0]out;
 universal_shift_register DUT(in, clk, reset, sel, out);
 initial
 begin
    clk = 0;
    forever #5 clk = ~clk;
 end
 initial
 begin
    $dumpfile("universal_shift_register_tb.vcd");
    $dumpvars(0, universal_shift_register_tb);
 end
 initial
 begin
    $display("universal shift register simulation");
    $monitor("time = %0t, in = %b, clk = %b, reset = %b, sel = %b, out = %b", $time, in, clk, reset, sel, out);
    in = 4'b1000; reset = 1'b0; sel = 2'b00; #5;
    in = 4'b1100; reset = 1'b0; sel = 2'b10; #10;
    in = 4'b0110; reset = 1'b1; sel = 2'b10; #10;
    in = 4'b1010; reset = 1'b0; sel = 2'b11; #10;
    in = 4'b1010; reset = 1'b0; sel = 2'b01; #10;
    in = 4'b1010; reset = 1'b0; sel = 2'b10; #10;
    in = 4'b1010; reset = 1'b0; sel = 2'b11; #10;
    in = 4'b1110; reset = 1'b0; sel = 2'b00; #10;
    in = 4'b1011; reset = 1'b0; sel = 2'b11; #10;
    $finish;
 end
endmodule

universal_shift_register_tb.vcd
$date
	Tue Jul 28 12:10:19 2026
$end
$version
	Icarus Verilog
$end
$timescale
	1s
$end
$scope module universal_shift_register_tb $end
$var wire 4 ! out [3:0] $end
$var reg 1 " clk $end
$var reg 4 # in [3:0] $end
$var reg 1 $ reset $end
$var reg 2 % sel [1:0] $end
$scope module DUT $end
$var wire 1 & clk $end
$var wire 4 ' in [3:0] $end
$var wire 1 ( reset $end
$var wire 2 ) sel [1:0] $end
$var reg 4 * out [3:0] $end
$upscope $end
$upscope $end
$enddefinitions $end
#0
$dumpvars
bx *
b0 )
0(
b1000 '
0&
b0 %
0$
b1000 #
0"
bx !
$end
#5
bx0 *
bx0 !
b10 %
b10 )
b1100 #
b1100 '
1"
1&
#10
0"
0&
#15
b0 *
b0 !
1"
1&
1$
1(
b110 #
b110 '
#20
0"
0&
#25
b1010 *
b1010 !
1"
1&
b11 %
b11 )
0$
0(
b1010 #
b1010 '
#30
0"
0&
#35
b101 *
b101 !
1"
1&
b1 %
b1 )
#40
0"
0&
#45
b1010 *
b1010 !
1"
1&
b10 %
b10 )
#50
0"
0&
#55
1"
1&
b11 %
b11 )
#60
0"
0&
#65
1"
1&
b0 %
b0 )
b1110 #
b1110 '
#70
0"
0&
#75
b1011 *
b1011 !
1"
1&
b11 %
b11 )
b1011 #
b1011 '
