up_down_counter.v
module up_down_counter(clk, reset, c_up, c_down, out);
 input clk, reset, c_up, c_down;
 output reg[3:0]out;
 always@(posedge clk)
 begin
    if(reset)
        out <= 4'b0000;
    else if(c_up)
        out <= out + 1;
    else if (c_down)
        out <= out - 1;
    else
        out <= out;
 end
endmodule

up_down_counter_tb.v
module up_down_counter_tb;
 reg clk, reset, c_up, c_down;
 wire [3:0]out;
 up_down_counter DUT(clk, reset, c_up, c_down, out);
 initial
 begin
    clk = 0;
    forever #5 clk = ~clk;
 end
 initial
 begin
    $dumpfile("up_down_counter_tb.vcd");
    $dumpvars(0, up_down_counter_tb);
 end
 initial
 begin
    $display("simulating up down counter");
    $monitor("time = %0t, clk = %b, reset = %b, c_up = %b, c_down = %b, out = %b", $time, clk, reset, c_up, c_down, out);
    reset = 1'b0; c_up = 1'b0; c_down = 1'b0; #5;
    reset = 1'b1; c_up = 1'b0; c_down = 1'b0; #10;
    reset = 1'b0; c_up = 1'b0; c_down = 1'b0; #10;
    reset = 1'b0; c_up = 1'b1; c_down = 1'b0; #10;
    reset = 1'b0; c_up = 1'b1; c_down = 1'b0; #10;
    reset = 1'b0; c_up = 1'b1; c_down = 1'b0; #10;
    reset = 1'b1; c_up = 1'b1; c_down = 1'b0; #10;
    reset = 1'b0; c_up = 1'b1; c_down = 1'b0; #10;
    reset = 1'b0; c_up = 1'b1; c_down = 1'b0; #10;
    reset = 1'b0; c_up = 1'b0; c_down = 1'b1; #10;
    reset = 1'b0; c_up = 1'b0; c_down = 1'b1; #10;
    reset = 1'b0; c_up = 1'b1; c_down = 1'b1; #10;
    reset = 1'b0; c_up = 1'b1; c_down = 1'b0; #10;
    reset = 1'b0; c_up = 1'b1; c_down = 1'b0; #10;
    reset = 1'b0; c_up = 1'b1; c_down = 1'b0; #10;
    $finish;
 end
endmodule

up_down_counter_tb.vcd
$date
	Tue Jul 28 12:53:04 2026
$end
$version
	Icarus Verilog
$end
$timescale
	1s
$end
$scope module up_down_counter_tb $end
$var wire 4 ! out [3:0] $end
$var reg 1 " c_down $end
$var reg 1 # c_up $end
$var reg 1 $ clk $end
$var reg 1 % reset $end
$scope module DUT $end
$var wire 1 & c_down $end
$var wire 1 ' c_up $end
$var wire 1 ( clk $end
$var wire 1 ) reset $end
$var reg 4 * out [3:0] $end
$upscope $end
$upscope $end
$enddefinitions $end
#0
$dumpvars
bx *
0)
0(
0'
0&
0%
0$
0#
0"
bx !
$end
#5
b0 *
b0 !
1%
1)
1$
1(
#10
0$
0(
#15
1$
1(
0%
0)
#20
0$
0(
#25
b1 *
b1 !
1$
1(
1#
1'
#30
0$
0(
#35
b10 *
b10 !
1$
1(
#40
0$
0(
#45
b11 *
b11 !
1$
1(
#50
0$
0(
#55
b0 *
b0 !
1$
1(
1%
1)
#60
0$
0(
#65
b1 *
b1 !
1$
1(
0%
0)
#70
0$
0(
#75
b10 *
b10 !
1$
1(
#80
0$
0(
#85
b1 *
b1 !
1$
1(
1"
1&
0#
0'
#90
0$
0(
#95
b0 *
b0 !
1$
1(
#100
0$
0(
#105
b1 *
b1 !
1$
1(
1#
1'
#110
0$
0(
#115
b10 *
b10 !
1$
1(
0"
0&
#120
0$
0(
#125
b11 *
b11 !
1$
1(
#130
0$
0(
#135
b100 *
b100 !
1$
1(
#140
0$
0(
#145
b101 *
b101 !
1$
1(
