frequency_divider/programmable_fd.v
module programmable_fd(clk, reset, sel, clk_out);
 input clk, reset;
 input [1:0]sel;
 output reg clk_out;
 reg [3:0]count;
 always@(posedge clk)
 begin
    if(reset)
        count = 4'b0000;
    else
        count = count + 1;
 end
 always@(*)
 begin
    case(sel)
        2'b00 : clk_out <= count[0];
        2'b01 : clk_out <= count[1];
        2'b10 : clk_out <= count[2];
        2'b11 : clk_out <= count[3];
        default : clk_out <= clk_out;
    endcase
 end
endmodule

frequency_divider/programmable_fd_tb.v
module programmable_fd_tb;
 reg clk, reset;
 reg [1:0]sel;
 wire clk_out;
 programmable_fd DUT(clk, reset, sel, clk_out);
 initial
 begin
    clk = 0;
    forever #5 clk = ~clk;
 end
 initial
 begin
    $dumpfile("programmable_fd_tb.vcd");
    $dumpvars(0, programmable_fd_tb);
 end

 initial
 begin
    $display("frequency divider by 2 simulation");
    $monitor("time = %0t, clk = %b, reset = %b, sel = %b, clk_out = %b", $time, clk, reset, sel, clk_out);
    reset = 1'b0; sel = 2'b00; #5;
    reset = 1'b1; sel = 2'b00; #10;
    reset = 1'b0; sel = 2'b00; #10;
    reset = 1'b0; sel = 2'b00; #10;
    reset = 1'b0; sel = 2'b01; #10;
    reset = 1'b0; sel = 2'b01; #10;
    reset = 1'b0; sel = 2'b01; #10;
    reset = 1'b0; sel = 2'b01; #10;
    reset = 1'b0; sel = 2'b01; #5;
    $finish;
 end
endmodule

frequency_divider/programmable_fd_tb.vcd
$date
	Tue Jul 28 15:12:08 2026
$end
$version
	Icarus Verilog
$end
$timescale
	1s
$end
$scope module programmable_fd_tb $end
$var wire 1 ! clk_out $end
$var reg 1 " clk $end
$var reg 1 # reset $end
$var reg 2 $ sel [1:0] $end
$scope module DUT $end
$var wire 1 % clk $end
$var wire 1 & reset $end
$var wire 2 ' sel [1:0] $end
$var reg 1 ( clk_out $end
$var reg 4 ) count [3:0] $end
$upscope $end
$upscope $end
$enddefinitions $end
#0
$dumpvars
bx )
x(
b0 '
0&
0%
b0 $
0#
0"
x!
$end
#5
0(
0!
b0 )
1#
1&
1"
1%
#10
0"
0%
#15
1(
1!
b1 )
1"
1%
0#
0&
#20
0"
0%
#25
0(
0!
b10 )
1"
1%
#30
0"
0%
#35
1(
1!
b11 )
1"
1%
b1 $
b1 '
#40
0"
0%
#45
0(
0!
b100 )
1"
1%
#50
0"
0%
#55
b101 )
1"
1%
#60
0"
0%
#65
1(
1!
b110 )
1"
1%
#70
0"
0%
#75
b111 )
1"
1%
