alu/alu.v
module alu(a, b, sel, out, carry, borrow);
 input [3:0] a, b;
 input [2:0] sel;
 output reg [3:0] out;
 output reg carry;
 output reg borrow;
 always@(*) begin
  out = 4'b0000;
  carry = 1'b0;
  borrow = 1'b0;
    if (sel == 3'b000)
        {carry, out} = {1'b0, a} + {1'b0, b};
    else if (sel == 3'b001) begin
        out = a - b;
        borrow = (a < b);
    end
    else if (sel == 3'b010)
        out = a & b;
    else if (sel == 3'b011)
        out = a | b;
    else if (sel == 3'b100)
        out = a ^ b;
    else if (sel == 3'b101)
        out = ~a;
    else if (sel == 3'b110)
        out = a << 2;
    else if (sel == 3'b111)
        out = (a > b) ? 4'b0001 : 4'b0000;
 end
endmodule

alu/alu_tb.v
module alu_tb;
 reg [3:0] a, b;
 reg [2:0] sel;
 wire [3:0] out;
 wire carry, borrow;
 alu DUT(a, b, sel, out, carry, borrow);
 initial
 begin
    $dumpfile("alu_tb.vcd");
    $dumpvars(0, alu_tb);
 end
 initial
 begin
    $display("simulation of alu");
    $monitor("a = %b, b = %b, sel = %b, out = %b, carry = %b, borrow = %b", a, b, sel, out, carry, borrow);
    a = 4'b0101; b = 4'b1011; sel = 3'b000; #10
    a = 4'b0101; b = 4'b1011; sel = 3'b001; #10
    a = 4'b0101; b = 4'b1011; sel = 3'b010; #10
    a = 4'b0101; b = 4'b1011; sel = 3'b011; #10
    a = 4'b0101; b = 4'b1011; sel = 3'b100; #10
    a = 4'b0101; b = 4'b1011; sel = 3'b101; #10
    a = 4'b0101; b = 4'b1011; sel = 3'b110; #10
    a = 4'b0101; b = 4'b1011; sel = 3'b111; #10
    $finish;
 end
endmodule

alu/alu_tb.vcd
$date
	Sun Jul 26 16:16:50 2026
$end
$version
	Icarus Verilog
$end
$timescale
	1s
$end
$scope module alu_tb $end
$var wire 1 ! borrow $end
$var wire 1 " carry $end
$var wire 4 # out [3:0] $end
$var reg 4 $ a [3:0] $end
$var reg 4 % b [3:0] $end
$var reg 3 & sel [2:0] $end
$scope module DUT $end
$var wire 4 ' a [3:0] $end
$var wire 4 ( b [3:0] $end
$var wire 3 ) sel [2:0] $end
$var reg 1 * borrow $end
$var reg 1 + carry $end
$var reg 4 , out [3:0] $end
$upscope $end
$upscope $end
$enddefinitions $end
#0
$dumpvars
b0 ,
1+
0*
b0 )
b1011 (
b101 '
b0 &
b1011 %
b101 $
b0 #
1"
0!
$end
#10
1*
1!
b1010 ,
b1010 #
0+
0"
b1 &
b1 )
#20
0*
0!
b1 ,
b1 #
b10 &
b10 )
#30
b1111 ,
b1111 #
b11 &
b11 )
#40
b1110 ,
b1110 #
b100 &
b100 )
#50
b1010 ,
b1010 #
b101 &
b101 )
#60
b100 ,
b100 #
b110 &
b110 )
#70
b0 ,
b0 #
b111 &
b111 )
